raven/__init__.py
raven/client.py
raven/core/__init__.py
raven/core/api_error.py
raven/core/datetime_utils.py
raven/core/jsonable_encoder.py
raven/core/remove_none_from_headers.py
raven/environment.py
raven/errors/__init__.py
raven/errors/event_not_found_error.py
raven/py.typed
raven/resources/__init__.py
raven/resources/device/__init__.py
raven/resources/device/client.py
raven/resources/device/types/__init__.py
raven/resources/device/types/device.py
raven/resources/device/types/platform.py
raven/resources/ids/__init__.py
raven/resources/ids/types/__init__.py
raven/resources/ids/types/app_id.py
raven/resources/ids/types/device_id.py
raven/resources/ids/types/request_id.py
raven/resources/ids/types/user_id.py
raven/resources/user/__init__.py
raven/resources/user/client.py
raven/resources/user/types/__init__.py
raven/resources/user/types/channel.py
raven/resources/user/types/channel_preference.py
raven/resources/user/types/channel_preferences.py
raven/resources/user/types/raven_user.py
raven/resources/user/types/slack_profile.py
raven/resources/user/types/telegram_profile.py
raven/resources/user/types/user_preferences.py
raven/types/__init__.py
raven/types/attachment.py
raven/types/batch_event.py
raven/types/channel_override.py
raven/types/email_message.py
raven/types/email_override.py
raven/types/email_recipient.py
raven/types/event_not_found_error_body.py
raven/types/event_override.py
raven/types/in_app_override.py
raven/types/param.py
raven/types/provider_override.py
raven/types/push_override.py
raven/types/send_event_response.py
raven/types/slack_message.py
raven/types/slack_override.py
raven/types/sms_message.py
raven/types/sms_override.py
raven/types/telegram_override.py
raven/types/user.py
raven/types/voice_override.py
raven/types/webhook_override.py
raven/types/whatsapp_override.py
ravendev-0.0.54.dist-info/METADATA
ravendev-0.0.54.dist-info/WHEEL
ravendev-0.0.54.dist-info/RECORD
