Metadata-Version: 2.1
Name: ravendev
Version: 0.0.54
Summary: 
Requires-Python: >=3.7,<4.0
Classifier: Programming Language :: Python :: 3
Classifier: Programming Language :: Python :: 3.7
Classifier: Programming Language :: Python :: 3.8
Classifier: Programming Language :: Python :: 3.9
Classifier: Programming Language :: Python :: 3.10
Classifier: Programming Language :: Python :: 3.11
Requires-Dist: backports-cached_property (==1.0.2)
Requires-Dist: httpx (==0.23.3)
Requires-Dist: pydantic (>=1.9.2,<2.0.0)
Requires-Dist: types-backports (==0.1.3)
